esteira/__init__.py
esteira/cli/__init__.py
esteira/pipeline/__init__.py
esteira/pipeline/runner.py
esteira/pipeline/service.py
esteira/pipeline/stage.py
esteira/pipeline/task.py
esteira/server/__init__.py
tests/__init__.py
tests/pipeline/__init__.py
tests/pipeline/test_runner.py
tests/pipeline/test_service.py
tests/pipeline/test_stage.py
tests/pipeline/test_task.py
tests/server/__init__.py
esteira-1.0.0.dist-info/LICENSE
esteira-1.0.0.dist-info/METADATA
esteira-1.0.0.dist-info/WHEEL
esteira-1.0.0.dist-info/top_level.txt
esteira-1.0.0.dist-info/RECORD
